interlo/__init__.py
interlo/interlo.py
interlo-1.1.2.dist-info/LICENSE
interlo-1.1.2.dist-info/METADATA
interlo-1.1.2.dist-info/WHEEL
interlo-1.1.2.dist-info/top_level.txt
interlo-1.1.2.dist-info/RECORD
